multiverse/__init__.py
unicorn_multiverse-0.0.3.dist-info/LICENSE.txt
unicorn_multiverse-0.0.3.dist-info/METADATA
unicorn_multiverse-0.0.3.dist-info/WHEEL
unicorn_multiverse-0.0.3.dist-info/top_level.txt
unicorn_multiverse-0.0.3.dist-info/RECORD
